rimteam_editor/__init__.py
rimteam_editor/__main__.py
rimteam_editor/automatic_gitting.py
rimteam_editor/line_builder.py
rimteam_editor/power.ini
rimteam_editor-0.1.26.dist-info/entry_points.txt
rimteam_editor-0.1.26.dist-info/WHEEL
rimteam_editor-0.1.26.dist-info/METADATA
rimteam_editor-0.1.26.dist-info/RECORD
