Metadata-Version: 2.1
Name: rimteam-editor
Version: 0.1.26
Summary: 
Author: RIM team
Requires-Python: >=3.7,<4.0
Classifier: Programming Language :: Python :: 3
Classifier: Programming Language :: Python :: 3.7
Requires-Dist: gitpython (>=3.0,<4.0)
Requires-Dist: requests (>=2.22,<3.0)
